swebench/__init__.py
swebench/collect/__init__.py
swebench/collect/build_dataset.py
swebench/collect/build_dataset_ft.py
swebench/collect/get_tasks_pipeline.py
swebench/collect/get_top_pypi.py
swebench/collect/print_pulls.py
swebench/collect/utils.py
swebench/harness/__init__.py
swebench/harness/docker_build.py
swebench/harness/docker_utils.py
swebench/harness/grading.py
swebench/harness/prepare_images.py
swebench/harness/remove_containers.py
swebench/harness/reporting.py
swebench/harness/run_evaluation.py
swebench/harness/utils.py
swebench/harness/constants/__init__.py
swebench/harness/constants/c.py
swebench/harness/constants/go.py
swebench/harness/constants/java.py
swebench/harness/constants/javascript.py
swebench/harness/constants/php.py
swebench/harness/constants/python.py
swebench/harness/constants/ruby.py
swebench/harness/constants/rust.py
swebench/harness/dockerfiles/__init__.py
swebench/harness/dockerfiles/c.py
swebench/harness/dockerfiles/go.py
swebench/harness/dockerfiles/java.py
swebench/harness/dockerfiles/javascript.py
swebench/harness/dockerfiles/php.py
swebench/harness/dockerfiles/python.py
swebench/harness/dockerfiles/ruby.py
swebench/harness/dockerfiles/rust.py
swebench/harness/log_parsers/__init__.py
swebench/harness/log_parsers/c.py
swebench/harness/log_parsers/go.py
swebench/harness/log_parsers/java.py
swebench/harness/log_parsers/javascript.py
swebench/harness/log_parsers/php.py
swebench/harness/log_parsers/python.py
swebench/harness/log_parsers/ruby.py
swebench/harness/log_parsers/rust.py
swebench/harness/modal_eval/__init__.py
swebench/harness/modal_eval/run_evaluation_modal.py
swebench/harness/modal_eval/run_evaluation_modal_entrypoint.py
swebench/harness/modal_eval/utils.py
swebench/harness/test_spec/__init__.py
swebench/harness/test_spec/create_scripts.py
swebench/harness/test_spec/javascript.py
swebench/harness/test_spec/python.py
swebench/harness/test_spec/test_spec.py
swebench/harness/test_spec/utils.py
swebench/inference/__init__.py
swebench-4.1.0.dist-info/licenses/LICENSE
swebench-4.1.0.dist-info/METADATA
swebench-4.1.0.dist-info/WHEEL
swebench-4.1.0.dist-info/top_level.txt
swebench-4.1.0.dist-info/RECORD
