Metadata-Version: 2.4
Name: swebench
Version: 4.1.0
Summary: The official SWE-bench package - a benchmark for evaluating LMs on software engineering
Author-email: SWE-bench team <support@swebench.com>
License: MIT License
Project-URL: Documentation, https://github.com/swe-bench/SWE-bench
Project-URL: Bug Reports, http://github.com/swe-bench/SWE-bench/issues
Project-URL: Source Code, http://github.com/swe-bench/SWE-bench
Project-URL: Website, https://swebench.com
Keywords: nlp,benchmark,code
Classifier: Programming Language :: Python :: 3.10
Classifier: Programming Language :: Python :: 3.11
Classifier: Programming Language :: Python :: 3 :: Only
Classifier: License :: OSI Approved :: MIT License
Classifier: Operating System :: OS Independent
Requires-Python: >=3.10
License-File: LICENSE
Requires-Dist: beautifulsoup4
Requires-Dist: chardet
Requires-Dist: datasets
Requires-Dist: docker
Requires-Dist: ghapi
Requires-Dist: GitPython
Requires-Dist: modal
Requires-Dist: pre-commit
Requires-Dist: python-dotenv
Requires-Dist: requests
Requires-Dist: rich
Requires-Dist: tenacity
Requires-Dist: tqdm
Requires-Dist: unidiff
Provides-Extra: datasets
Requires-Dist: protobuf; extra == "datasets"
Requires-Dist: sentencepiece; extra == "datasets"
Requires-Dist: tiktoken; extra == "datasets"
Requires-Dist: transformers; extra == "datasets"
Requires-Dist: openai; extra == "datasets"
Requires-Dist: anthropic; extra == "datasets"
Requires-Dist: jedi; extra == "datasets"
Provides-Extra: inference
Requires-Dist: torch>=2.0.0; extra == "inference"
Requires-Dist: anthropic; extra == "inference"
Requires-Dist: jedi; extra == "inference"
Requires-Dist: openai; extra == "inference"
Requires-Dist: peft; extra == "inference"
Requires-Dist: protobuf; extra == "inference"
Requires-Dist: sentencepiece; extra == "inference"
Requires-Dist: tiktoken; extra == "inference"
Requires-Dist: transformers; extra == "inference"
Requires-Dist: triton; extra == "inference"
Requires-Dist: flash_attn>=2.0.0; extra == "inference"
Requires-Dist: requests; extra == "inference"
Provides-Extra: test
Requires-Dist: pytest; extra == "test"
Requires-Dist: pytest-cov; extra == "test"
Provides-Extra: docs
Requires-Dist: mkdocs; extra == "docs"
Requires-Dist: mkdocs-material; extra == "docs"
Requires-Dist: mkdocs-glightbox; extra == "docs"
Requires-Dist: mkdocstrings; extra == "docs"
Requires-Dist: mkdocstrings-python; extra == "docs"
Requires-Dist: mike; extra == "docs"
Requires-Dist: pymdown-extensions; extra == "docs"
Requires-Dist: mkdocs-include-markdown-plugin; extra == "docs"
Dynamic: license-file
